fastai_slack/__init__.py
fastai_slack/_version.py
fastai_slack-0.1.3.dist-info/LICENSE
fastai_slack-0.1.3.dist-info/METADATA
fastai_slack-0.1.3.dist-info/WHEEL
fastai_slack-0.1.3.dist-info/top_level.txt
fastai_slack-0.1.3.dist-info/RECORD
