Metadata-Version: 2.1
Name: fastai-slack
Version: 0.1.3
Summary: Slack notifications for FastAI model training
Home-page: https://github.com/swiftace-ai/fastai_slack
Author: SwiftAce
Author-email: opensource@swiftace.ai
License: UNKNOWN
Platform: UNKNOWN
Classifier: Programming Language :: Python :: 3
Classifier: License :: OSI Approved :: MIT License
Classifier: Operating System :: OS Independent
Requires-Dist: requests
